promptflow/_cli/__init__.py
promptflow/_cli/_completers/_param_completers.py
promptflow/_cli/_params.py
promptflow/_cli/_pf/__init__.py
promptflow/_cli/_pf/_config.py
promptflow/_cli/_pf/_connection.py
promptflow/_cli/_pf/_experiment.py
promptflow/_cli/_pf/_flow.py
promptflow/_cli/_pf/_init_entry_generators.py
promptflow/_cli/_pf/_run.py
promptflow/_cli/_pf/_service.py
promptflow/_cli/_pf/_tool.py
promptflow/_cli/_pf/_trace.py
promptflow/_cli/_pf/_upgrade.py
promptflow/_cli/_pf/entry.py
promptflow/_cli/_pf/help.py
promptflow/_cli/_user_agent.py
promptflow/_cli/_utils.py
promptflow/_cli/data/chat_flow/flow_files/.promptflow/flow.tools.json
promptflow/_cli/data/chat_flow/flow_files/README.md
promptflow/_cli/data/chat_flow/flow_files/chat.jinja2
promptflow/_cli/data/chat_flow/template/azure_openai.yaml.jinja2
promptflow/_cli/data/chat_flow/template/flow.dag.yaml.jinja2
promptflow/_cli/data/chat_flow/template/openai.yaml.jinja2
promptflow/_cli/data/entry_flow/flow.dag.yaml.jinja2
promptflow/_cli/data/entry_flow/flow.tools.json.jinja2
promptflow/_cli/data/entry_flow/gitignore
promptflow/_cli/data/entry_flow/requirements_txt
promptflow/_cli/data/entry_flow/tool.py.jinja2
promptflow/_cli/data/evaluation_flow/.promptflow/flow.tools.json
promptflow/_cli/data/evaluation_flow/aggregate.py
promptflow/_cli/data/evaluation_flow/data.jsonl
promptflow/_cli/data/evaluation_flow/flow.dag.yaml
promptflow/_cli/data/evaluation_flow/line_process.py
promptflow/_cli/data/package_tool/README.md.jinja2
promptflow/_cli/data/package_tool/init.py
promptflow/_cli/data/package_tool/setup.py.jinja2
promptflow/_cli/data/package_tool/tool.py.jinja2
promptflow/_cli/data/package_tool/utils.py.jinja2
promptflow/_cli/data/standard_flow/.promptflow/flow.tools.json
promptflow/_cli/data/standard_flow/data.jsonl
promptflow/_cli/data/standard_flow/flow.dag.yaml
promptflow/_cli/data/standard_flow/hello.jinja2
promptflow/_cli/data/standard_flow/hello.py
promptflow/_cli/pf.py
promptflow_devkit-1.18.2.dist-info/METADATA
promptflow_devkit-1.18.2.dist-info/WHEEL
promptflow_devkit-1.18.2.dist-info/entry_points.txt
promptflow_devkit-1.18.2.dist-info/RECORD
