Metadata-Version: 2.4
Name: promptflow-devkit
Version: 1.18.2
Summary: Prompt flow devkit
License: MIT
Keywords: devkit
Author: Microsoft Corporation
Author-email: aml-pt-eng@microsoft.com
Requires-Python: >=3.9, !=2.7.*, !=3.0.*, !=3.1.*, !=3.2.*, !=3.3.*, !=3.4.*, !=3.5.*, !=3.6.*, !=3.7.*, !=3.8.*, !=3.14.*
Classifier: License :: OSI Approved :: MIT License
Classifier: Operating System :: OS Independent
Classifier: Programming Language :: Python
Classifier: Programming Language :: Python :: 3
Classifier: Programming Language :: Python :: 3.9
Classifier: Programming Language :: Python :: 3.10
Classifier: Programming Language :: Python :: 3.11
Classifier: Programming Language :: Python :: 3.12
Classifier: Programming Language :: Python :: 3.13
Classifier: Programming Language :: Python :: 3 :: Only
Classifier: Programming Language :: Python :: 3.14
Provides-Extra: executable
Provides-Extra: pyarrow
Requires-Dist: argcomplete (>=3.2.3)
Requires-Dist: azure-monitor-opentelemetry-exporter (>=1.0.0b21,<2.0.0)
Requires-Dist: bs4 ; extra == "executable"
Requires-Dist: colorama (>=0.4.6,<0.5.0)
Requires-Dist: cryptography (>=42.0.4)
Requires-Dist: filelock (>=3.4.0,<4.0.0)
Requires-Dist: flask-cors (>=6.0.0,<7.0.0)
Requires-Dist: flask-restx (>=1.2.0,<2.0.0)
Requires-Dist: gitpython (>=3.1.24,<4.0.0)
Requires-Dist: httpx (>=0.25.1)
Requires-Dist: keyring (>=24.2.0,<25.0.0)
Requires-Dist: marshmallow (>=3.5,<4.0.0)
Requires-Dist: opentelemetry-exporter-otlp-proto-http (>=1.22.0,<2.0.0)
Requires-Dist: pandas (>=1.5.3,<3.0.0)
Requires-Dist: pillow (>=10.1.0,<=11.3.0)
Requires-Dist: promptflow-core (>=1.18.2,<2.0.0)
Requires-Dist: pyarrow (>=14.0.1,<15.0.0) ; extra == "executable" or extra == "pyarrow"
Requires-Dist: pydash (>=6.0.0,<8.0.0)
Requires-Dist: pyinstaller (>=5.13.2) ; extra == "executable"
Requires-Dist: python-dotenv (>=1.0.0,<2.0.0)
Requires-Dist: pywin32 ; sys_platform == "win32"
Requires-Dist: sqlalchemy (>=1.4.48,<3.0.0)
Requires-Dist: streamlit (>=1.26.0) ; extra == "executable"
Requires-Dist: streamlit-quill (<0.1.0) ; extra == "executable"
Requires-Dist: strictyaml (>=1.5.0,<2.0.0)
Requires-Dist: tabulate (>=0.9.0,<1.0.0)
Requires-Dist: waitress (>=3.0.0,<4.0.0)
Project-URL: Bug Reports, https://github.com/microsoft/promptflow/issues
Project-URL: Homepage, https://microsoft.github.io/promptflow/
Project-URL: Repository, https://github.com/microsoft/promptflow
